presentation/__init__.py
presentation/presentation_creator.py
presentation/presentation_processor.py
copilot4office-0.2.dist-info/LICENSE
copilot4office-0.2.dist-info/METADATA
copilot4office-0.2.dist-info/WHEEL
copilot4office-0.2.dist-info/top_level.txt
copilot4office-0.2.dist-info/RECORD
