Metadata-Version: 2.1
Name: copilot4office
Version: 0.2
Summary: ChatGPT copilot for office files
Author: Faisal Rehman
Author-email: fslurrehman@gmail.com
License: MIT
Classifier: Development Status :: 3 - Alpha
Classifier: Intended Audience :: Developers
Classifier: License :: OSI Approved :: MIT License
Classifier: Programming Language :: Python :: 3
Requires-Python: >=3.6
License-File: LICENSE
Requires-Dist: python-pptx
